gregutils/__init__.py
gregutils/main.py
gregutils-0.0.3.dist-info/METADATA
gregutils-0.0.3.dist-info/WHEEL
gregutils-0.0.3.dist-info/licenses/LICENSE
gregutils-0.0.3.dist-info/RECORD
