Metadata-Version: 2.1
Name: gregutils
Version: 0.0.3
Summary: Usefull utils
Project-URL: Homepage, https://github.com/afanasev90/gregutils
Project-URL: Bug Tracker, https://github.com/afanasev90/gregutils/issues
Author-email: Anton Afanasev <web.afanasyev@gmail.com>
License-File: LICENSE
Classifier: License :: OSI Approved :: MIT License
Classifier: Operating System :: OS Independent
Classifier: Programming Language :: Python :: 3
Requires-Python: >=3.7
